{
  "name": "Totient Ratio",
  "scales": [
    1,
    2,
    5,
    10
  ],
  "n_trials": 20,
  "size": 2000,
  "metrics": [
    "E8 Lattice:alignment_mean:tau1",
    "E8 Lattice:alignment_std:tau1",
    "E8 Lattice:diversity_ratio:tau1",
    "E8 Lattice:entropy:tau1",
    "E8 Lattice:normalized_entropy:tau1",
    "E8 Lattice:unique_roots:tau1",
    "Torus T^2:chi2_uniformity:tau1",
    "Torus T^2:coverage:tau1",
    "Torus T^2:entropy:tau1",
    "Torus T^2:normalized_entropy:tau1",
    "Torus T^2:occupied_bins:tau1",
    "Hyperbolic (Poincar\u00e9):boundary_proximity:tau1",
    "Hyperbolic (Poincar\u00e9):centroid_norm:tau1",
    "Hyperbolic (Poincar\u00e9):dispersion:tau1",
    "Hyperbolic (Poincar\u00e9):mean_hyperbolic_radius:tau1",
    "Hyperbolic (Poincar\u00e9):mean_radius:tau1",
    "Heisenberg (Nil):final_z:tau1",
    "Heisenberg (Nil):path_length:tau1",
    "Heisenberg (Nil):twist_rate:tau1",
    "Heisenberg (Nil):xy_spread:tau1",
    "Heisenberg (Nil):z_variance:tau1",
    "Heisenberg (Nil) (centered):final_z:tau1",
    "Heisenberg (Nil) (centered):path_length:tau1",
    "Heisenberg (Nil) (centered):twist_rate:tau1",
    "Heisenberg (Nil) (centered):xy_spread:tau1",
    "Heisenberg (Nil) (centered):z_variance:tau1",
    "Spherical S\u00b2:angular_spread:tau1",
    "Spherical S\u00b2:concentration:tau1",
    "Spherical S\u00b2:hemisphere_balance:tau1",
    "Spherical S\u00b2:mean_z:tau1",
    "Sol (Thurston):anisotropy:tau1",
    "Sol (Thurston):path_length:tau1",
    "Sol (Thurston):stretch_ratio:tau1",
    "Sol (Thurston):z_drift:tau1",
    "Sol (Thurston):z_variance:tau1",
    "S\u00b2 \u00d7 \u211d (Thurston):height_drift:tau1",
    "S\u00b2 \u00d7 \u211d (Thurston):height_variance:tau1",
    "S\u00b2 \u00d7 \u211d (Thurston):sphere_concentration:tau1",
    "S\u00b2 \u00d7 \u211d (Thurston):sphere_height_corr:tau1",
    "S\u00b2 \u00d7 \u211d (Thurston):winding_number:tau1",
    "H\u00b2 \u00d7 \u211d (Thurston):boundary_proximity:tau1",
    "H\u00b2 \u00d7 \u211d (Thurston):depth_height_corr:tau1",
    "H\u00b2 \u00d7 \u211d (Thurston):height_drift:tau1",
    "H\u00b2 \u00d7 \u211d (Thurston):height_variance:tau1",
    "H\u00b2 \u00d7 \u211d (Thurston):hyperbolic_variance:tau1",
    "H\u00b2 \u00d7 \u211d (Thurston):mean_hyperbolic_distance:tau1",
    "SL(2,\u211d) (Thurston):elliptic_fraction:tau1",
    "SL(2,\u211d) (Thurston):final_trace:tau1",
    "SL(2,\u211d) (Thurston):hyperbolic_fraction:tau1",
    "SL(2,\u211d) (Thurston):mean_spectral_radius:tau1",
    "SL(2,\u211d) (Thurston):mean_trace:tau1",
    "SL(2,\u211d) (Thurston):parabolic_fraction:tau1",
    "2-adic:distance_entropy:tau1",
    "2-adic:mean_distance:tau1",
    "2-adic:ultrametric_violation_rate:tau1",
    "Cantor (base 3):coverage:tau1",
    "Cantor (base 3):estimated_dimension:tau1",
    "Cantor (base 3):max_gap:tau1",
    "Cantor (base 3):mean_gap:tau1",
    "Tropical:linearity:tau1",
    "Tropical:slope_changes:tau1",
    "Tropical:tropical_hull_area:tau1",
    "Tropical:unique_slopes:tau1",
    "Projective \u2119\u00b2:collinearity:tau1",
    "Projective \u2119\u00b2:cross_ratio_std:tau1",
    "Projective \u2119\u00b2:distance_std:tau1",
    "Projective \u2119\u00b2:mean_distance:tau1",
    "Wasserstein:concentration:tau1",
    "Wasserstein:dist_from_uniform:tau1",
    "Wasserstein:entropy:tau1",
    "Wasserstein:normalized_entropy:tau1",
    "Wasserstein:self_similarity:tau1",
    "Fisher Information:det_fisher:tau1",
    "Fisher Information:effective_dimension:tau1",
    "Fisher Information:jeffreys_volume:tau1",
    "Fisher Information:kl_from_uniform:tau1",
    "Fisher Information:trace_fisher:tau1",
    "Persistent Homology:max_components:tau1",
    "Persistent Homology:max_lifetime:tau1",
    "Persistent Homology:n_significant_features:tau1",
    "Persistent Homology:persistence_entropy:tau1",
    "Persistent Homology:total_persistence:tau1",
    "Lorentzian:causal_order_preserved:tau1",
    "Lorentzian:lightlike_fraction:tau1",
    "Lorentzian:mean_velocity:tau1",
    "Lorentzian:spacelike_fraction:tau1",
    "Lorentzian:superluminal_fraction:tau1",
    "Lorentzian:timelike_fraction:tau1",
    "Symplectic:area_variation:tau1",
    "Symplectic:min_return_distance:tau1",
    "Symplectic:p_spread:tau1",
    "Symplectic:q_spread:tau1",
    "Symplectic:total_area:tau1",
    "Spiral (logarithmic):angular_uniformity:tau1",
    "Spiral (logarithmic):final_radius:tau1",
    "Spiral (logarithmic):growth_rate:tau1",
    "Spiral (logarithmic):tightness:tau1",
    "Spiral (logarithmic):total_winding:tau1",
    "Penrose (Quasicrystal):fivefold_balance:tau1",
    "Penrose (Quasicrystal):golden_ratio_score:tau1",
    "Penrose (Quasicrystal):index_diversity:tau1",
    "Penrose (Quasicrystal):long_range_order:tau1",
    "Ammann-Beenker (Octagonal):eightfold_balance:tau1",
    "Ammann-Beenker (Octagonal):index_diversity:tau1",
    "Ammann-Beenker (Octagonal):long_range_order:tau1",
    "Ammann-Beenker (Octagonal):silver_ratio_score:tau1",
    "Ammann-Beenker (Octagonal):square_diag_ratio:tau1",
    "Einstein (Hat Monotile):chirality:tau1",
    "Einstein (Hat Monotile):hex_asymmetry:tau1",
    "Einstein (Hat Monotile):hexagonal_balance:tau1",
    "Einstein (Hat Monotile):index_diversity:tau1",
    "Einstein (Hat Monotile):long_range_order:tau1",
    "Clifford Torus:path_regularity:tau1",
    "Clifford Torus:phi_coverage:tau1",
    "Clifford Torus:phi_linearity_r2:tau1",
    "Clifford Torus:phi_slope:tau1",
    "Clifford Torus:phi_winding:tau1",
    "Clifford Torus:theta_coverage:tau1",
    "Clifford Torus:theta_linearity_r2:tau1",
    "Clifford Torus:theta_slope:tau1",
    "Clifford Torus:theta_winding:tau1",
    "Higher-Order Statistics:bicoherence_max:tau1",
    "Higher-Order Statistics:bicoherence_mean:tau1",
    "Higher-Order Statistics:c3_energy:tau1",
    "Higher-Order Statistics:c3_mean:tau1",
    "Higher-Order Statistics:kurt_max:tau1",
    "Higher-Order Statistics:kurt_mean:tau1",
    "Higher-Order Statistics:perm_entropy:tau1",
    "Higher-Order Statistics:perm_forbidden:tau1",
    "Higher-Order Statistics:skew_max:tau1",
    "Higher-Order Statistics:skew_mean:tau1",
    "E8 Lattice:alignment_mean:tau2",
    "E8 Lattice:alignment_std:tau2",
    "E8 Lattice:diversity_ratio:tau2",
    "E8 Lattice:entropy:tau2",
    "E8 Lattice:normalized_entropy:tau2",
    "E8 Lattice:unique_roots:tau2",
    "Torus T^2:chi2_uniformity:tau2",
    "Torus T^2:coverage:tau2",
    "Torus T^2:entropy:tau2",
    "Torus T^2:normalized_entropy:tau2",
    "Torus T^2:occupied_bins:tau2",
    "Hyperbolic (Poincar\u00e9):boundary_proximity:tau2",
    "Hyperbolic (Poincar\u00e9):centroid_norm:tau2",
    "Hyperbolic (Poincar\u00e9):dispersion:tau2",
    "Hyperbolic (Poincar\u00e9):mean_hyperbolic_radius:tau2",
    "Hyperbolic (Poincar\u00e9):mean_radius:tau2",
    "Heisenberg (Nil):final_z:tau2",
    "Heisenberg (Nil):path_length:tau2",
    "Heisenberg (Nil):twist_rate:tau2",
    "Heisenberg (Nil):xy_spread:tau2",
    "Heisenberg (Nil):z_variance:tau2",
    "Heisenberg (Nil) (centered):final_z:tau2",
    "Heisenberg (Nil) (centered):path_length:tau2",
    "Heisenberg (Nil) (centered):twist_rate:tau2",
    "Heisenberg (Nil) (centered):xy_spread:tau2",
    "Heisenberg (Nil) (centered):z_variance:tau2",
    "Spherical S\u00b2:angular_spread:tau2",
    "Spherical S\u00b2:concentration:tau2",
    "Spherical S\u00b2:hemisphere_balance:tau2",
    "Spherical S\u00b2:mean_z:tau2",
    "Sol (Thurston):anisotropy:tau2",
    "Sol (Thurston):path_length:tau2",
    "Sol (Thurston):stretch_ratio:tau2",
    "Sol (Thurston):z_drift:tau2",
    "Sol (Thurston):z_variance:tau2",
    "S\u00b2 \u00d7 \u211d (Thurston):height_drift:tau2",
    "S\u00b2 \u00d7 \u211d (Thurston):height_variance:tau2",
    "S\u00b2 \u00d7 \u211d (Thurston):sphere_concentration:tau2",
    "S\u00b2 \u00d7 \u211d (Thurston):sphere_height_corr:tau2",
    "S\u00b2 \u00d7 \u211d (Thurston):winding_number:tau2",
    "H\u00b2 \u00d7 \u211d (Thurston):boundary_proximity:tau2",
    "H\u00b2 \u00d7 \u211d (Thurston):depth_height_corr:tau2",
    "H\u00b2 \u00d7 \u211d (Thurston):height_drift:tau2",
    "H\u00b2 \u00d7 \u211d (Thurston):height_variance:tau2",
    "H\u00b2 \u00d7 \u211d (Thurston):hyperbolic_variance:tau2",
    "H\u00b2 \u00d7 \u211d (Thurston):mean_hyperbolic_distance:tau2",
    "SL(2,\u211d) (Thurston):elliptic_fraction:tau2",
    "SL(2,\u211d) (Thurston):final_trace:tau2",
    "SL(2,\u211d) (Thurston):hyperbolic_fraction:tau2",
    "SL(2,\u211d) (Thurston):mean_spectral_radius:tau2",
    "SL(2,\u211d) (Thurston):mean_trace:tau2",
    "SL(2,\u211d) (Thurston):parabolic_fraction:tau2",
    "2-adic:distance_entropy:tau2",
    "2-adic:mean_distance:tau2",
    "2-adic:ultrametric_violation_rate:tau2",
    "Cantor (base 3):coverage:tau2",
    "Cantor (base 3):estimated_dimension:tau2",
    "Cantor (base 3):max_gap:tau2",
    "Cantor (base 3):mean_gap:tau2",
    "Tropical:linearity:tau2",
    "Tropical:slope_changes:tau2",
    "Tropical:tropical_hull_area:tau2",
    "Tropical:unique_slopes:tau2",
    "Projective \u2119\u00b2:collinearity:tau2",
    "Projective \u2119\u00b2:cross_ratio_std:tau2",
    "Projective \u2119\u00b2:distance_std:tau2",
    "Projective \u2119\u00b2:mean_distance:tau2",
    "Wasserstein:concentration:tau2",
    "Wasserstein:dist_from_uniform:tau2",
    "Wasserstein:entropy:tau2",
    "Wasserstein:normalized_entropy:tau2",
    "Wasserstein:self_similarity:tau2",
    "Fisher Information:det_fisher:tau2",
    "Fisher Information:effective_dimension:tau2",
    "Fisher Information:jeffreys_volume:tau2",
    "Fisher Information:kl_from_uniform:tau2",
    "Fisher Information:trace_fisher:tau2",
    "Persistent Homology:max_components:tau2",
    "Persistent Homology:max_lifetime:tau2",
    "Persistent Homology:n_significant_features:tau2",
    "Persistent Homology:persistence_entropy:tau2",
    "Persistent Homology:total_persistence:tau2",
    "Lorentzian:causal_order_preserved:tau2",
    "Lorentzian:lightlike_fraction:tau2",
    "Lorentzian:mean_velocity:tau2",
    "Lorentzian:spacelike_fraction:tau2",
    "Lorentzian:superluminal_fraction:tau2",
    "Lorentzian:timelike_fraction:tau2",
    "Symplectic:area_variation:tau2",
    "Symplectic:min_return_distance:tau2",
    "Symplectic:p_spread:tau2",
    "Symplectic:q_spread:tau2",
    "Symplectic:total_area:tau2",
    "Spiral (logarithmic):angular_uniformity:tau2",
    "Spiral (logarithmic):final_radius:tau2",
    "Spiral (logarithmic):growth_rate:tau2",
    "Spiral (logarithmic):tightness:tau2",
    "Spiral (logarithmic):total_winding:tau2",
    "Penrose (Quasicrystal):fivefold_balance:tau2",
    "Penrose (Quasicrystal):golden_ratio_score:tau2",
    "Penrose (Quasicrystal):index_diversity:tau2",
    "Penrose (Quasicrystal):long_range_order:tau2",
    "Ammann-Beenker (Octagonal):eightfold_balance:tau2",
    "Ammann-Beenker (Octagonal):index_diversity:tau2",
    "Ammann-Beenker (Octagonal):long_range_order:tau2",
    "Ammann-Beenker (Octagonal):silver_ratio_score:tau2",
    "Ammann-Beenker (Octagonal):square_diag_ratio:tau2",
    "Einstein (Hat Monotile):chirality:tau2",
    "Einstein (Hat Monotile):hex_asymmetry:tau2",
    "Einstein (Hat Monotile):hexagonal_balance:tau2",
    "Einstein (Hat Monotile):index_diversity:tau2",
    "Einstein (Hat Monotile):long_range_order:tau2",
    "Clifford Torus:path_regularity:tau2",
    "Clifford Torus:phi_coverage:tau2",
    "Clifford Torus:phi_linearity_r2:tau2",
    "Clifford Torus:phi_slope:tau2",
    "Clifford Torus:phi_winding:tau2",
    "Clifford Torus:theta_coverage:tau2",
    "Clifford Torus:theta_linearity_r2:tau2",
    "Clifford Torus:theta_slope:tau2",
    "Clifford Torus:theta_winding:tau2",
    "Higher-Order Statistics:bicoherence_max:tau2",
    "Higher-Order Statistics:bicoherence_mean:tau2",
    "Higher-Order Statistics:c3_energy:tau2",
    "Higher-Order Statistics:c3_mean:tau2",
    "Higher-Order Statistics:kurt_max:tau2",
    "Higher-Order Statistics:kurt_mean:tau2",
    "Higher-Order Statistics:perm_entropy:tau2",
    "Higher-Order Statistics:perm_forbidden:tau2",
    "Higher-Order Statistics:skew_max:tau2",
    "Higher-Order Statistics:skew_mean:tau2",
    "E8 Lattice:alignment_mean:tau5",
    "E8 Lattice:alignment_std:tau5",
    "E8 Lattice:diversity_ratio:tau5",
    "E8 Lattice:entropy:tau5",
    "E8 Lattice:normalized_entropy:tau5",
    "E8 Lattice:unique_roots:tau5",
    "Torus T^2:chi2_uniformity:tau5",
    "Torus T^2:coverage:tau5",
    "Torus T^2:entropy:tau5",
    "Torus T^2:normalized_entropy:tau5",
    "Torus T^2:occupied_bins:tau5",
    "Hyperbolic (Poincar\u00e9):boundary_proximity:tau5",
    "Hyperbolic (Poincar\u00e9):centroid_norm:tau5",
    "Hyperbolic (Poincar\u00e9):dispersion:tau5",
    "Hyperbolic (Poincar\u00e9):mean_hyperbolic_radius:tau5",
    "Hyperbolic (Poincar\u00e9):mean_radius:tau5",
    "Heisenberg (Nil):final_z:tau5",
    "Heisenberg (Nil):path_length:tau5",
    "Heisenberg (Nil):twist_rate:tau5",
    "Heisenberg (Nil):xy_spread:tau5",
    "Heisenberg (Nil):z_variance:tau5",
    "Heisenberg (Nil) (centered):final_z:tau5",
    "Heisenberg (Nil) (centered):path_length:tau5",
    "Heisenberg (Nil) (centered):twist_rate:tau5",
    "Heisenberg (Nil) (centered):xy_spread:tau5",
    "Heisenberg (Nil) (centered):z_variance:tau5",
    "Spherical S\u00b2:angular_spread:tau5",
    "Spherical S\u00b2:concentration:tau5",
    "Spherical S\u00b2:hemisphere_balance:tau5",
    "Spherical S\u00b2:mean_z:tau5",
    "Sol (Thurston):anisotropy:tau5",
    "Sol (Thurston):path_length:tau5",
    "Sol (Thurston):stretch_ratio:tau5",
    "Sol (Thurston):z_drift:tau5",
    "Sol (Thurston):z_variance:tau5",
    "S\u00b2 \u00d7 \u211d (Thurston):height_drift:tau5",
    "S\u00b2 \u00d7 \u211d (Thurston):height_variance:tau5",
    "S\u00b2 \u00d7 \u211d (Thurston):sphere_concentration:tau5",
    "S\u00b2 \u00d7 \u211d (Thurston):sphere_height_corr:tau5",
    "S\u00b2 \u00d7 \u211d (Thurston):winding_number:tau5",
    "H\u00b2 \u00d7 \u211d (Thurston):boundary_proximity:tau5",
    "H\u00b2 \u00d7 \u211d (Thurston):depth_height_corr:tau5",
    "H\u00b2 \u00d7 \u211d (Thurston):height_drift:tau5",
    "H\u00b2 \u00d7 \u211d (Thurston):height_variance:tau5",
    "H\u00b2 \u00d7 \u211d (Thurston):hyperbolic_variance:tau5",
    "H\u00b2 \u00d7 \u211d (Thurston):mean_hyperbolic_distance:tau5",
    "SL(2,\u211d) (Thurston):elliptic_fraction:tau5",
    "SL(2,\u211d) (Thurston):final_trace:tau5",
    "SL(2,\u211d) (Thurston):hyperbolic_fraction:tau5",
    "SL(2,\u211d) (Thurston):mean_spectral_radius:tau5",
    "SL(2,\u211d) (Thurston):mean_trace:tau5",
    "SL(2,\u211d) (Thurston):parabolic_fraction:tau5",
    "2-adic:distance_entropy:tau5",
    "2-adic:mean_distance:tau5",
    "2-adic:ultrametric_violation_rate:tau5",
    "Cantor (base 3):coverage:tau5",
    "Cantor (base 3):estimated_dimension:tau5",
    "Cantor (base 3):max_gap:tau5",
    "Cantor (base 3):mean_gap:tau5",
    "Tropical:linearity:tau5",
    "Tropical:slope_changes:tau5",
    "Tropical:tropical_hull_area:tau5",
    "Tropical:unique_slopes:tau5",
    "Projective \u2119\u00b2:collinearity:tau5",
    "Projective \u2119\u00b2:cross_ratio_std:tau5",
    "Projective \u2119\u00b2:distance_std:tau5",
    "Projective \u2119\u00b2:mean_distance:tau5",
    "Wasserstein:concentration:tau5",
    "Wasserstein:dist_from_uniform:tau5",
    "Wasserstein:entropy:tau5",
    "Wasserstein:normalized_entropy:tau5",
    "Wasserstein:self_similarity:tau5",
    "Fisher Information:det_fisher:tau5",
    "Fisher Information:effective_dimension:tau5",
    "Fisher Information:jeffreys_volume:tau5",
    "Fisher Information:kl_from_uniform:tau5",
    "Fisher Information:trace_fisher:tau5",
    "Persistent Homology:max_components:tau5",
    "Persistent Homology:max_lifetime:tau5",
    "Persistent Homology:n_significant_features:tau5",
    "Persistent Homology:persistence_entropy:tau5",
    "Persistent Homology:total_persistence:tau5",
    "Lorentzian:causal_order_preserved:tau5",
    "Lorentzian:lightlike_fraction:tau5",
    "Lorentzian:mean_velocity:tau5",
    "Lorentzian:spacelike_fraction:tau5",
    "Lorentzian:superluminal_fraction:tau5",
    "Lorentzian:timelike_fraction:tau5",
    "Symplectic:area_variation:tau5",
    "Symplectic:min_return_distance:tau5",
    "Symplectic:p_spread:tau5",
    "Symplectic:q_spread:tau5",
    "Symplectic:total_area:tau5",
    "Spiral (logarithmic):angular_uniformity:tau5",
    "Spiral (logarithmic):final_radius:tau5",
    "Spiral (logarithmic):growth_rate:tau5",
    "Spiral (logarithmic):tightness:tau5",
    "Spiral (logarithmic):total_winding:tau5",
    "Penrose (Quasicrystal):fivefold_balance:tau5",
    "Penrose (Quasicrystal):golden_ratio_score:tau5",
    "Penrose (Quasicrystal):index_diversity:tau5",
    "Penrose (Quasicrystal):long_range_order:tau5",
    "Ammann-Beenker (Octagonal):eightfold_balance:tau5",
    "Ammann-Beenker (Octagonal):index_diversity:tau5",
    "Ammann-Beenker (Octagonal):long_range_order:tau5",
    "Ammann-Beenker (Octagonal):silver_ratio_score:tau5",
    "Ammann-Beenker (Octagonal):square_diag_ratio:tau5",
    "Einstein (Hat Monotile):chirality:tau5",
    "Einstein (Hat Monotile):hex_asymmetry:tau5",
    "Einstein (Hat Monotile):hexagonal_balance:tau5",
    "Einstein (Hat Monotile):index_diversity:tau5",
    "Einstein (Hat Monotile):long_range_order:tau5",
    "Clifford Torus:path_regularity:tau5",
    "Clifford Torus:phi_coverage:tau5",
    "Clifford Torus:phi_linearity_r2:tau5",
    "Clifford Torus:phi_slope:tau5",
    "Clifford Torus:phi_winding:tau5",
    "Clifford Torus:theta_coverage:tau5",
    "Clifford Torus:theta_linearity_r2:tau5",
    "Clifford Torus:theta_slope:tau5",
    "Clifford Torus:theta_winding:tau5",
    "Higher-Order Statistics:bicoherence_max:tau5",
    "Higher-Order Statistics:bicoherence_mean:tau5",
    "Higher-Order Statistics:c3_energy:tau5",
    "Higher-Order Statistics:c3_mean:tau5",
    "Higher-Order Statistics:kurt_max:tau5",
    "Higher-Order Statistics:kurt_mean:tau5",
    "Higher-Order Statistics:perm_entropy:tau5",
    "Higher-Order Statistics:perm_forbidden:tau5",
    "Higher-Order Statistics:skew_max:tau5",
    "Higher-Order Statistics:skew_mean:tau5",
    "E8 Lattice:alignment_mean:tau10",
    "E8 Lattice:alignment_std:tau10",
    "E8 Lattice:diversity_ratio:tau10",
    "E8 Lattice:entropy:tau10",
    "E8 Lattice:normalized_entropy:tau10",
    "E8 Lattice:unique_roots:tau10",
    "Torus T^2:chi2_uniformity:tau10",
    "Torus T^2:coverage:tau10",
    "Torus T^2:entropy:tau10",
    "Torus T^2:normalized_entropy:tau10",
    "Torus T^2:occupied_bins:tau10",
    "Hyperbolic (Poincar\u00e9):boundary_proximity:tau10",
    "Hyperbolic (Poincar\u00e9):centroid_norm:tau10",
    "Hyperbolic (Poincar\u00e9):dispersion:tau10",
    "Hyperbolic (Poincar\u00e9):mean_hyperbolic_radius:tau10",
    "Hyperbolic (Poincar\u00e9):mean_radius:tau10",
    "Heisenberg (Nil):final_z:tau10",
    "Heisenberg (Nil):path_length:tau10",
    "Heisenberg (Nil):twist_rate:tau10",
    "Heisenberg (Nil):xy_spread:tau10",
    "Heisenberg (Nil):z_variance:tau10",
    "Heisenberg (Nil) (centered):final_z:tau10",
    "Heisenberg (Nil) (centered):path_length:tau10",
    "Heisenberg (Nil) (centered):twist_rate:tau10",
    "Heisenberg (Nil) (centered):xy_spread:tau10",
    "Heisenberg (Nil) (centered):z_variance:tau10",
    "Spherical S\u00b2:angular_spread:tau10",
    "Spherical S\u00b2:concentration:tau10",
    "Spherical S\u00b2:hemisphere_balance:tau10",
    "Spherical S\u00b2:mean_z:tau10",
    "Sol (Thurston):anisotropy:tau10",
    "Sol (Thurston):path_length:tau10",
    "Sol (Thurston):stretch_ratio:tau10",
    "Sol (Thurston):z_drift:tau10",
    "Sol (Thurston):z_variance:tau10",
    "S\u00b2 \u00d7 \u211d (Thurston):height_drift:tau10",
    "S\u00b2 \u00d7 \u211d (Thurston):height_variance:tau10",
    "S\u00b2 \u00d7 \u211d (Thurston):sphere_concentration:tau10",
    "S\u00b2 \u00d7 \u211d (Thurston):sphere_height_corr:tau10",
    "S\u00b2 \u00d7 \u211d (Thurston):winding_number:tau10",
    "H\u00b2 \u00d7 \u211d (Thurston):boundary_proximity:tau10",
    "H\u00b2 \u00d7 \u211d (Thurston):depth_height_corr:tau10",
    "H\u00b2 \u00d7 \u211d (Thurston):height_drift:tau10",
    "H\u00b2 \u00d7 \u211d (Thurston):height_variance:tau10",
    "H\u00b2 \u00d7 \u211d (Thurston):hyperbolic_variance:tau10",
    "H\u00b2 \u00d7 \u211d (Thurston):mean_hyperbolic_distance:tau10",
    "SL(2,\u211d) (Thurston):elliptic_fraction:tau10",
    "SL(2,\u211d) (Thurston):final_trace:tau10",
    "SL(2,\u211d) (Thurston):hyperbolic_fraction:tau10",
    "SL(2,\u211d) (Thurston):mean_spectral_radius:tau10",
    "SL(2,\u211d) (Thurston):mean_trace:tau10",
    "SL(2,\u211d) (Thurston):parabolic_fraction:tau10",
    "2-adic:distance_entropy:tau10",
    "2-adic:mean_distance:tau10",
    "2-adic:ultrametric_violation_rate:tau10",
    "Cantor (base 3):coverage:tau10",
    "Cantor (base 3):estimated_dimension:tau10",
    "Cantor (base 3):max_gap:tau10",
    "Cantor (base 3):mean_gap:tau10",
    "Tropical:linearity:tau10",
    "Tropical:slope_changes:tau10",
    "Tropical:tropical_hull_area:tau10",
    "Tropical:unique_slopes:tau10",
    "Projective \u2119\u00b2:collinearity:tau10",
    "Projective \u2119\u00b2:cross_ratio_std:tau10",
    "Projective \u2119\u00b2:distance_std:tau10",
    "Projective \u2119\u00b2:mean_distance:tau10",
    "Wasserstein:concentration:tau10",
    "Wasserstein:dist_from_uniform:tau10",
    "Wasserstein:entropy:tau10",
    "Wasserstein:normalized_entropy:tau10",
    "Wasserstein:self_similarity:tau10",
    "Fisher Information:det_fisher:tau10",
    "Fisher Information:effective_dimension:tau10",
    "Fisher Information:jeffreys_volume:tau10",
    "Fisher Information:kl_from_uniform:tau10",
    "Fisher Information:trace_fisher:tau10",
    "Persistent Homology:max_components:tau10",
    "Persistent Homology:max_lifetime:tau10",
    "Persistent Homology:n_significant_features:tau10",
    "Persistent Homology:persistence_entropy:tau10",
    "Persistent Homology:total_persistence:tau10",
    "Lorentzian:causal_order_preserved:tau10",
    "Lorentzian:lightlike_fraction:tau10",
    "Lorentzian:mean_velocity:tau10",
    "Lorentzian:spacelike_fraction:tau10",
    "Lorentzian:superluminal_fraction:tau10",
    "Lorentzian:timelike_fraction:tau10",
    "Symplectic:area_variation:tau10",
    "Symplectic:min_return_distance:tau10",
    "Symplectic:p_spread:tau10",
    "Symplectic:q_spread:tau10",
    "Symplectic:total_area:tau10",
    "Spiral (logarithmic):angular_uniformity:tau10",
    "Spiral (logarithmic):final_radius:tau10",
    "Spiral (logarithmic):growth_rate:tau10",
    "Spiral (logarithmic):tightness:tau10",
    "Spiral (logarithmic):total_winding:tau10",
    "Penrose (Quasicrystal):fivefold_balance:tau10",
    "Penrose (Quasicrystal):golden_ratio_score:tau10",
    "Penrose (Quasicrystal):index_diversity:tau10",
    "Penrose (Quasicrystal):long_range_order:tau10",
    "Ammann-Beenker (Octagonal):eightfold_balance:tau10",
    "Ammann-Beenker (Octagonal):index_diversity:tau10",
    "Ammann-Beenker (Octagonal):long_range_order:tau10",
    "Ammann-Beenker (Octagonal):silver_ratio_score:tau10",
    "Ammann-Beenker (Octagonal):square_diag_ratio:tau10",
    "Einstein (Hat Monotile):chirality:tau10",
    "Einstein (Hat Monotile):hex_asymmetry:tau10",
    "Einstein (Hat Monotile):hexagonal_balance:tau10",
    "Einstein (Hat Monotile):index_diversity:tau10",
    "Einstein (Hat Monotile):long_range_order:tau10",
    "Clifford Torus:path_regularity:tau10",
    "Clifford Torus:phi_coverage:tau10",
    "Clifford Torus:phi_linearity_r2:tau10",
    "Clifford Torus:phi_slope:tau10",
    "Clifford Torus:phi_winding:tau10",
    "Clifford Torus:theta_coverage:tau10",
    "Clifford Torus:theta_linearity_r2:tau10",
    "Clifford Torus:theta_slope:tau10",
    "Clifford Torus:theta_winding:tau10",
    "Higher-Order Statistics:bicoherence_max:tau10",
    "Higher-Order Statistics:bicoherence_mean:tau10",
    "Higher-Order Statistics:c3_energy:tau10",
    "Higher-Order Statistics:c3_mean:tau10",
    "Higher-Order Statistics:kurt_max:tau10",
    "Higher-Order Statistics:kurt_mean:tau10",
    "Higher-Order Statistics:perm_entropy:tau10",
    "Higher-Order Statistics:perm_forbidden:tau10",
    "Higher-Order Statistics:skew_max:tau10",
    "Higher-Order Statistics:skew_mean:tau10"
  ],
  "means": [
    2.420987587193328,
    0.11448314636114461,
    0.04583333333333333,
    1.4553289994819951,
    0.18405832000385638,
    11.0,
    10467.443199732032,
    0.2083984375,
    4.961283301110654,
    0.6201604126388317,
    53.35,
    0.39255000000000007,
    0.5808613952340372,
    1.349767703774389,
    1.8385637801531511,
    0.5996866169011681,
    14862.9042495194,
    14932.00841475751,
    14.862904249519403,
    120.79721790675197,
    19680163.57057514,
    349419.8681473496,
    365276.23039180547,
    349.41986814734975,
    483.1210795037774,
    10876880457.99501,
    0.3120537043111371,
    0.6998691422539671,
    0.02180000000000002,
    -0.215504097086853,
    53.87601627768494,
    31699.763055188225,
    29.405389828641923,
    6.789803921568615,
    8.232563240627249,
    0.003137254901960784,
    0.04642203212318309,
    0.41125010572083254,
    -0.8953552894949766,
    -0.6984313725490197,
    0.3961711711711712,
    -0.058916463912857986,
    0.003137254901960784,
    0.04642203212318309,
    1.7399608675759937,
    1.8464239996992529,
    0.0,
    2.564268747460832e+53,
    1.0,
    1.1540944121542154,
    2.0200274760731376,
    0.0,
    2.057527639103932,
    0.658217256310419,
    0.0,
    0.08184999999999999,
    0.7595342473690555,
    0.33348574912360907,
    0.0004492262897185523,
    0.0019019019019019035,
    1994.2,
    783.6427450980393,
    5.0,
    0.9635000000000001,
    832656.2496262402,
    0.25499547368326336,
    0.3700418117052964,
    5.440799999982997,
    0.10358984375108622,
    4.066332945845527,
    0.8132665891691054,
    0.9980171875000062,
    5.580192127351626e+21,
    8.63956911275798,
    74594922037.71205,
    0.32394962730626686,
    531.157020223938,
    100.0,
    1.3781975422361517,
    5.75,
    5.3960393602559,
    5.456680323486774,
    0.0018009004502251122,
    0.0,
    811.7097764568559,
    0.4317198396793587,
    0.9981990995497749,
    0.5682801603206413,
    0.22683955041885487,
    0.0032205261147303455,
    0.4590116167719504,
    0.2418948185760897,
    24.871715494040778,
    0.9999999999999186,
    345466423.69307435,
    0.009999886956651249,
    10858577.053985935,
    31.815073124069908,
    0.7346120691701487,
    0.45510642135642126,
    0.0778,
    0.3041808582575004,
    0.7378362018194534,
    0.058650000000000015,
    0.3041808582575004,
    0.07331349206349207,
    0.9630350463663542,
    0.9806497343795337,
    1.0918456773090333,
    0.7351804668699762,
    0.04080000000000001,
    0.3041808582575004,
    3.05418562045503,
    0.46875,
    0.3063559070576491,
    -0.0024341358020411458,
    -0.1443137254901961,
    0.46875,
    0.2946695927435011,
    -0.0035926940981408856,
    -0.297843137254902,
    1.035816484089501,
    0.3593145879647358,
    0.7511697137730872,
    0.09355274084899887,
    1.2777234903909218,
    -1.0820478582803816,
    0.6175670248667177,
    0.6558333333333333,
    0.4164231034272693,
    0.2303708359903629,
    2.4623388354889424,
    0.1036920502178029,
    0.04166666666666666,
    1.4415761275567927,
    0.18231896725084862,
    10.0,
    4738.316799878698,
    0.4318359375,
    5.9855182086148835,
    0.7481897760768604,
    110.55,
    0.3505999999999999,
    0.25159292329871236,
    1.4631075763657795,
    1.787632283265085,
    0.5661459569309135,
    5573.18479008074,
    10757.703188031477,
    5.573184790080739,
    30.563149437266013,
    2767933.4832688533,
    274.5450927573676,
    1502.0944223977092,
    0.2745450927573676,
    0.6590820923187896,
    6276.389298388533,
    0.4174145263452907,
    0.32348990629066693,
    0.9803999999999998,
    -0.21555322571586114,
    65.10272846368937,
    19471.05198738768,
    33.69830712630059,
    7.550294117647047,
    8.807302149368395,
    0.000588235294117645,
    0.048063252939165184,
    0.35837881532191773,
    0.926458943462278,
    -1.042549019607843,
    0.364039039039039,
    -0.3862712859563325,
    0.000588235294117645,
    0.048063252939165184,
    1.8864173225883771,
    1.7948947617739919,
    0.0,
    9.349621346448088e+58,
    1.0,
    1.2508807744841843,
    2.0629217246304963,
    0.0,
    2.0607233491570645,
    0.6572381343984963,
    0.0,
    0.06772500000000001,
    0.7594318072678795,
    0.33357719859777457,
    0.000448570573962488,
    0.01466466466466465,
    1968.7,
    769.0949019607843,
    5.2,
    0.7154999999999999,
    14852.522878451424,
    0.20372895994923082,
    0.4001806615880681,
    5.384799999983173,
    0.10361953125108611,
    4.058356118861221,
    0.8116712237722444,
    0.9972671875000085,
    4.5698038562357846e+21,
    7.855476628466631,
    66146719520.09566,
    0.3024537055520369,
    540.0896110364253,
    100.0,
    1.351683659317097,
    18.4,
    5.8124838431689545,
    7.479363467351561,
    0.0231615807903952,
    0.0,
    587.5775142473196,
    0.42314268537074157,
    0.976838419209605,
    0.5768573146292584,
    0.08369721153391654,
    0.004244967742876115,
    0.360878287769811,
    0.24193276044107576,
    105.2772821991543,
    0.9999999999999186,
    336142220.8725687,
    0.009999901845863819,
    10565502.045667883,
    31.815073124069908,
    0.784056002421311,
    0.3578796571075983,
    0.1362,
    0.4384671814575591,
    0.7805130886519674,
    0.11070000000000002,
    0.4384671814575591,
    0.1973513333072157,
    1.048768805668707,
    0.4028497843410591,
    1.0426492776683816,
    0.7842508621552184,
    0.08470000000000001,
    0.4384671814575591,
    6.676944684838103,
    0.8125,
    0.5240951598410559,
    0.013123121877921109,
    1.500588235294118,
    0.8125,
    0.5244571764474147,
    0.013101913356483285,
    1.5641176470588236,
    1.048863281708012,
    0.3459698259271392,
    0.4666730911885336,
    0.07173923822176101,
    1.525256380391993,
    -1.1005380367885578,
    0.6045775317870261,
    0.6854166666666666,
    0.5305133123121741,
    0.3379789344363923,
    2.4476725092787004,
    0.14352767186331405,
    0.046874999999999986,
    1.8651824270666295,
    0.2358932888362652,
    11.25,
    5947.839999847734,
    0.3625,
    5.7198146689078815,
    0.7149768336134852,
    92.8,
    0.3819,
    0.2692810520396689,
    1.1913208513514257,
    1.792998413875815,
    0.6071739879420724,
    5615.591054594389,
    10801.458023578312,
    5.615591054594388,
    30.56314736814799,
    2807048.9562443867,
    441.2838420036542,
    1476.1149659416878,
    0.4412838420036542,
    0.7120864657580186,
    16253.511057995376,
    0.5786946386371556,
    0.2591638072692664,
    0.9803999999999998,
    -0.21555322571586114,
    66.87627144831343,
    21457.981506124685,
    34.23464680468169,
    7.551039215686261,
    8.807267322513008,
    0.003921568627450972,
    0.04807504356398753,
    0.3531029192970703,
    0.9265002784401689,
    1.0052941176470587,
    0.35728228228228226,
    -0.4040770921561606,
    0.003921568627450972,
    0.04807504356398753,
    1.6805840083038768,
    1.772746363137681,
    0.0,
    5.837075299542958e+58,
    1.0,
    1.2529153876327122,
    2.063995251987291,
    0.0,
    2.0632560845863708,
    0.6575737949785179,
    0.0,
    0.0678,
    0.7594318072678795,
    0.33357719859777457,
    0.000448570573962488,
    0.007132132132132113,
    1983.75,
    769.6754901960784,
    9.75,
    0.6905,
    108798.89505627504,
    0.20421065788817355,
    0.3973954689648094,
    5.386399999983168,
    0.10361875000108614,
    4.0583620658804564,
    0.8116724131760915,
    0.9972875000000085,
    4.5757234632357115e+21,
    7.856669166776278,
    66166392615.807495,
    0.30253036896980984,
    540.0593247839953,
    100.0,
    1.2924629305124067,
    19.3,
    5.783796508287152,
    7.372662173237612,
    0.02133566783391696,
    0.0,
    586.4453795525212,
    0.42689250629773606,
    0.9786643321660831,
    0.573107493702264,
    0.07871236786362315,
    0.004791532181294583,
    0.3571022692995741,
    0.24192765872364713,
    105.27445290272992,
    0.9999999999999186,
    339061920.7456564,
    0.009999895190494,
    10657273.007868486,
    31.815073124069908,
    0.7011945317930488,
    0.3578796571075983,
    0.11830000000000003,
    0.4384671814575591,
    0.6905464189308398,
    0.0896,
    0.4384671814575591,
    0.1973513333072157,
    1.0981652561683979,
    0.5425816014264482,
    1.0779734564033188,
    0.7023372456470021,
    0.06924999999999998,
    0.4384671814575591,
    4.758429509747314,
    0.8125,
    0.5236671612038859,
    0.01313731320532697,
    1.5045098039215683,
    0.8125,
    0.5244571764474147,
    0.013101913356483285,
    1.5641176470588236,
    1.023513708776028,
    0.3513419493185702,
    0.4517286197135804,
    0.07020855425339363,
    1.4008972032561144,
    -1.1197652609819178,
    0.7700597519421575,
    0.5108333333333331,
    0.4658798756208212,
    0.2569664240346653,
    2.43831311462235,
    0.12147773371932011,
    0.058750000000000004,
    1.5017838346565047,
    0.1899335543469634,
    14.1,
    6288.729599839009,
    0.3890625,
    5.718100540280696,
    0.714762567535087,
    99.6,
    0.3293,
    0.24710605377711187,
    1.4830994896449474,
    1.7569432321983296,
    0.5549244719360216,
    5568.374138408306,
    10756.470359925395,
    5.568374138408307,
    30.562935883302906,
    2763897.4929907513,
    348.312076583379,
    1499.7213783583898,
    0.348312076583379,
    0.6608545950727813,
    10125.016914960932,
    0.4284222476166499,
    0.3383200474272377,
    0.9803999999999998,
    -0.21555322571586114,
    42.940928055021686,
    13074.478605548273,
    21.578798368447114,
    7.1709607843137295,
    5.3929988871923085,
    -0.017254901960784316,
    0.05569424329927566,
    0.35251319498340594,
    0.847607120531684,
    -6.756862745098023,
    0.33731231231231235,
    -0.40457255872917897,
    -0.017254901960784316,
    0.05569424329927566,
    1.4940008416797406,
    1.7419861184759657,
    0.0,
    3.662034465318989e+48,
    1.0,
    1.2576130762577358,
    2.0677574665170773,
    0.0,
    2.0526473024325975,
    0.6587547495972073,
    0.0,
    0.06787500000000002,
    0.7594318072678795,
    0.33357719859777457,
    0.000448570573962488,
    0.021371371371371368,
    1955.3,
    770.2713725490196,
    8.6,
    0.7649999999999999,
    29.516979525579284,
    0.23036121506957316,
    0.41431439806722337,
    5.387199999983166,
    0.10361796875108616,
    4.058684309608173,
    0.8117368619216343,
    0.9973234375000084,
    4.55052164155949e+21,
    7.872121267412534,
    66013811227.501076,
    0.3023937270668847,
    539.6398703219833,
    100.0,
    1.2812848604439226,
    14.45,
    5.704762398415404,
    6.911014428886935,
    0.031390695347673844,
    0.0,
    573.4373068887386,
    0.4365089810142373,
    0.9686093046523261,
    0.5634910189857627,
    0.07080562351181283,
    0.002931538160709541,
    0.33375303265768774,
    0.2419249026101947,
    105.26841560938098,
    0.9999999999999186,
    341322333.55062735,
    0.009999874017154476,
    10728321.494733468,
    31.815073124069908,
    0.758100478866395,
    0.3578796571075983,
    0.12785000000000002,
    0.4384671814575591,
    0.7529526249587899,
    0.10145000000000001,
    0.4384671814575591,
    0.1973513333072157,
    1.0619918642473736,
    -0.37933465269094674,
    1.0346292505902475,
    0.758450218925113,
    0.0823,
    0.4384671814575591,
    6.662125455616502,
    0.8125,
    0.5228490176922762,
    0.013133302858502546,
    1.6470588235294117,
    0.8125,
    0.5244571764474147,
    0.013101913356483285,
    1.5641176470588236,
    1.04423021975489,
    0.3561862967211219,
    0.3222411432488255,
    0.06148147111824766,
    1.4555035794073248,
    -1.1284357889505992,
    0.7343059363702256,
    0.53125,
    0.53188764505087,
    0.3504612170637042
  ],
  "stds": [
    0.0020355961432127053,
    0.001674367399159995,
    0.0037267799624996515,
    0.058494843844658216,
    0.007397957912449957,
    0.8944271909999159,
    207.96733340490118,
    0.005562121431991463,
    0.01335442278518857,
    0.0016693028481485712,
    1.4239030865898146,
    0.003368605052540298,
    0.00031075956152200475,
    0.008840675036666223,
    0.003381484354187782,
    0.00030640980454054405,
    23.571701722867786,
    32.61391373559598,
    0.023571701722867853,
    0.05653495324776173,
    45094.086352498765,
    369.5904596936184,
    15721.119258205914,
    0.3695904596936229,
    0.24656496932115823,
    21155965.927789345,
    0.10392152191976863,
    0.14115096446395414,
    0.021971800108320682,
    0.5030954494445801,
    54.474118910791915,
    23834.461876247893,
    30.41485093894389,
    7.2412317238246,
    5.460641588550958,
    0.40259175727975854,
    0.015278081074732663,
    0.16289466695006202,
    0.010643318117708718,
    3.7115814462285073,
    0.10120974981939017,
    0.5988630593585126,
    0.40259175727975854,
    0.015278081074732663,
    0.8151955281971378,
    0.23006356933379907,
    0.0,
    3.5116266688981344e+53,
    0.0,
    0.03797608387335613,
    0.008384294458211877,
    0.0,
    0.02247979453714176,
    0.004394038942575337,
    0.0,
    0.0014840822079655843,
    2.220446049250313e-16,
    1.1102230246251565e-16,
    4.5747610888196004e-08,
    0.0006448497861223667,
    1.2884098726725126,
    7.8257707635133595,
    0.6324555320336759,
    0.01796524422322168,
    3447762.1783038313,
    0.02475175400769046,
    0.022794399158057536,
    0.07092080089768099,
    0.00016409039941300986,
    0.009033721721372661,
    0.001806744344274529,
    0.0003680972771807821,
    5.864659334773492e+20,
    0.4026934313372591,
    3973629768.774239,
    0.0055496347878116956,
    14.396266072503465,
    0.0,
    0.01844884448840266,
    1.6393596310755,
    0.05804328162291224,
    0.09518159068214116,
    0.00043033142906666463,
    0.0,
    0.3780591813564984,
    0.020068940697339523,
    0.0004303314290666612,
    0.020068940697339503,
    0.09987886798555255,
    0.004429071857507514,
    0.00016943699151711556,
    0.00010060789952498189,
    0.07472932040701755,
    3.3306690738754696e-16,
    125690690.51246321,
    5.041227030281228e-07,
    3950664.8373747133,
    7.105427357601002e-15,
    0.0016358767607936215,
    0.36658139495724673,
    0.00506557005676558,
    0.0005921358225585621,
    0.0004109087856747781,
    0.002815581645060217,
    0.0005921358225585621,
    0.09609853336427367,
    0.00035099647518582814,
    0.0027915668130474754,
    0.05802430463613722,
    0.0013275350902049378,
    0.0013638181696985858,
    0.0005921358225585621,
    0.013979079166044617,
    0.15625,
    0.35406462540904177,
    0.016239831795226124,
    2.019291656193332,
    0.15625,
    0.3493213100069915,
    0.01616004106127325,
    2.1553914678902073,
    0.0867827976143508,
    0.008291653618595927,
    0.0038670976092821468,
    0.0002654971361691292,
    0.00409080383310336,
    0.006410234245573912,
    0.002468959216617388,
    0.012388390622765397,
    0.008354174405409073,
    0.0017566744615528092,
    0.0029326122767591354,
    0.0022858022067998485,
    0.004750730937913077,
    0.08791322895881408,
    0.011118558919689747,
    1.140175425099138,
    510.58790936136756,
    0.01333141948951682,
    0.09331335986454209,
    0.011664169983067761,
    3.412843389316306,
    0.003072458299147439,
    0.00031039654733033535,
    0.012049050230814163,
    0.007430348450550725,
    0.00043563869359342826,
    12.157127067470725,
    16.09720185543725,
    0.01215712706747074,
    0.02375233103773715,
    12629.27427828896,
    0.7640281544272098,
    78.66987288101988,
    0.0007640281544272109,
    0.09279515194949133,
    29.147921935738974,
    0.0015699694783532457,
    0.000756029899336751,
    0.002497999199359362,
    0.00041687379444182017,
    62.2913616879152,
    12976.539308357651,
    32.436307497101005,
    6.951477037347453,
    5.248780500147177,
    0.4392529308438385,
    0.014655209691137438,
    0.14651760512410658,
    0.008371682649038245,
    3.641280109815664,
    0.09188094279113992,
    0.4000901180348171,
    0.4392529308438385,
    0.014655209691137438,
    0.3615334910192869,
    0.2706779227752833,
    0.0,
    1.2965007638545557e+59,
    0.0,
    0.010521343765033608,
    0.008443635626649088,
    0.0,
    0.014366378258444118,
    0.002795286931040029,
    0.0,
    0.0012794041581923998,
    0.00044652604879250366,
    0.00027434842249658426,
    1.0830155760437639e-06,
    0.0019963634309488696,
    3.9887341350358265,
    13.474002798103676,
    0.39999999999999997,
    0.03747999466382033,
    64673.02837801683,
    0.01676122894221373,
    0.009065820352504764,
    0.06909240189753242,
    0.0003430844053275518,
    0.01932930899791456,
    0.003865861799582908,
    0.0004758293540938007,
    1.8576197448610928e+21,
    1.4962978350142973,
    13943290607.513823,
    0.025575594186276758,
    77.2838327505771,
    0.0,
    0.02766962580668387,
    3.0066592756745814,
    0.044882445324456455,
    0.15909312211467616,
    0.001783446070032605,
    0.0,
    0.6922571830944154,
    0.02333392795752425,
    0.001783446070032612,
    0.023333927957524234,
    0.014149739885976773,
    0.007046029453606875,
    0.00034991877221682397,
    0.00021516570246126487,
    0.1961490414279762,
    3.3306690738754696e-16,
    112445400.38702558,
    8.287065812487371e-07,
    3534343.614833615,
    7.105427357601002e-15,
    0.0005803366876891475,
    0.09141538219921566,
    0.006712674578735359,
    0.00046522514220469745,
    0.0006114650125339597,
    0.002100000000000002,
    0.00046522514220469745,
    0.08075646396731079,
    0.00027499057808951053,
    0.001847791184720064,
    0.00202302735123318,
    0.0005908319234931555,
    0.0025317977802344293,
    0.00046522514220469745,
    0.04117504430277077,
    0.0,
    0.27109732699248557,
    0.053791561339425906,
    7.97062207503127,
    0.0,
    0.27071590627695646,
    0.053801251581163535,
    8.057798157658075,
    0.09179827647773567,
    0.010318024043341804,
    0.004327895357268799,
    0.00033243771457502566,
    0.0034662274298829544,
    0.004470250549377065,
    0.0027103702711390397,
    0.022496141644488467,
    0.00518241696488985,
    0.0025810397149472323,
    0.011024589679860414,
    0.039083302111914894,
    0.007201827507268169,
    0.4024112778044134,
    0.050893745517095225,
    1.7284386017443605,
    636.2522666126017,
    0.01678324301479753,
    0.10873906341496646,
    0.013592382926870808,
    4.296510211788168,
    0.004515528761950258,
    0.0003019990277786399,
    0.006609199017705204,
    0.003191435480699472,
    0.0004847692371703006,
    21.998234141352054,
    30.3071273656121,
    0.021998234141352112,
    0.023644733413977066,
    12752.805488494427,
    0.38866478852389563,
    73.94347679305704,
    0.00038866478852389537,
    0.10393511028066407,
    47.84628945793478,
    0.002308751226194046,
    0.0006511644122253273,
    0.002497999199359362,
    0.00041687379444182017,
    64.68421576470703,
    14149.586792086022,
    33.158042654794734,
    6.952609454585323,
    5.248774411947003,
    0.1035100992088022,
    0.01466083908781245,
    0.14622489788520138,
    0.008379295283904008,
    3.8099768410597674,
    0.09134693237787266,
    0.41153168631953113,
    0.1035100992088022,
    0.01466083908781245,
    0.4952969856402639,
    0.2837869509591792,
    0.0,
    8.731646932805419e+58,
    0.0,
    0.009750304431908904,
    0.008780790907931298,
    0.0,
    0.01643259101086958,
    0.002886504681520737,
    0.0,
    0.001298075498574718,
    0.00044652604879250366,
    0.00027434842249658426,
    1.0830155760437645e-06,
    0.0016285504908432437,
    3.253843880704789,
    13.436150395374975,
    0.698212002188447,
    0.04295055296500848,
    394742.3820994852,
    0.017056628760148813,
    0.009753826270789839,
    0.06304791828423181,
    0.0003300316627792152,
    0.01909421817647093,
    0.0038188436352941846,
    0.000498885476585989,
    1.8820521384532538e+21,
    1.4976373920521888,
    14061719363.09801,
    0.025594192880774958,
    77.35991880465617,
    0.0,
    0.03533323553515722,
    2.6095976701399772,
    0.0557757514366891,
    0.20398371092171996,
    0.0017635147310727688,
    0.0,
    0.6133465709970012,
    0.0219553285194346,
    0.0017635147310727534,
    0.021955328519434582,
    0.01008860239766766,
    0.0056924986741259806,
    0.00024767459088672705,
    0.00017196580090227413,
    0.3061377077105561,
    3.3306690738754696e-16,
    125404678.1327977,
    3.035183891957834e-07,
    3941674.9887999534,
    7.105427357601002e-15,
    0.00045394687110030684,
    0.09141538219921566,
    0.004371498598878878,
    0.00046522514220469745,
    0.0005096848557158311,
    0.0027640549922170496,
    0.00046522514220469745,
    0.08075646396731079,
    0.0003315828865675166,
    0.0022629562279494744,
    0.000999648464387185,
    0.0004689837671404542,
    0.0025074887836239635,
    0.00046522514220469745,
    0.020062638890269595,
    0.0,
    0.27148992064758726,
    0.05379147950169465,
    7.985289654424059,
    0.0,
    0.27071590627695646,
    0.053801251581163535,
    8.057798157658075,
    0.0598106607745647,
    0.009955523668755612,
    0.0036537519712105063,
    0.0003100029771738348,
    0.002690821439127626,
    0.0025792859865110354,
    0.002831442961150949,
    0.030516389039334263,
    0.004845855937845872,
    0.0025120637028304333,
    0.0019915317620492643,
    0.00234185979514911,
    0.006305310812675649,
    0.06632412973738651,
    0.008388143093091847,
    1.513274595042156,
    726.6786545234443,
    0.015249391637455579,
    0.10896973838273567,
    0.013621217297841959,
    3.903844259188628,
    0.0025514701644346167,
    0.0002793504754471947,
    0.006652840991709731,
    0.003735166751021774,
    0.0003083802100694082,
    16.692114036655344,
    23.455735891650566,
    0.01669211403665531,
    0.023489640783983957,
    12633.748464896447,
    0.7114145555483976,
    47.46989315526649,
    0.000711414555548397,
    0.06498690019073076,
    29.869382375313847,
    0.0009690313016854981,
    0.0008316986795754498,
    0.002497999199359362,
    0.00041687379444182017,
    46.482740877740255,
    16096.517574781317,
    20.841210010102536,
    3.6212290666953595,
    5.027812283605318,
    0.45282555183222256,
    0.0014864682401204414,
    0.10660262317414748,
    0.049247496151460936,
    101.18784234618995,
    0.1009499056513605,
    0.21242535432527235,
    0.45282555183222256,
    0.0014864682401204414,
    0.8002622075001168,
    0.16218084722802745,
    0.0,
    5.655398939915744e+48,
    0.0,
    0.048943987884545556,
    0.021546711779484508,
    0.0,
    0.015613094975627979,
    0.0029222355155352413,
    0.0,
    0.001283306276771061,
    0.00044652604879250366,
    0.00027434842249658426,
    1.0830155760437645e-06,
    0.0016531676241154807,
    3.303028912982749,
    13.588492066724806,
    0.48989794855663554,
    0.03943348830626071,
    34.8340149636271,
    0.022366781532634494,
    0.02754807460389739,
    0.06957700769629102,
    0.0003211488699638331,
    0.018863131230863833,
    0.0037726262461727673,
    0.0004996360980425554,
    1.8486035280438404e+21,
    1.506562546243562,
    13881583799.384916,
    0.025398329105780125,
    77.54689262447735,
    0.0,
    0.0404515550192535,
    2.376446927663229,
    0.05858899615321465,
    0.20732379970450426,
    0.0014744654980679834,
    0.0,
    0.37888466681988425,
    0.01834777081412409,
    0.0014744654980679978,
    0.018347770814124073,
    0.024393329482081297,
    0.004625424303448161,
    0.0002039175388726696,
    0.0001459848299520601,
    0.10612430642568453,
    3.3306690738754696e-16,
    116256774.65755038,
    9.273069593666768e-07,
    3654141.3683428476,
    7.105427357601002e-15,
    0.00038894374240440785,
    0.09141538219921566,
    0.006271164166245375,
    0.00046522514220469745,
    0.00041596827491196175,
    0.002765411361804964,
    0.00046522514220469745,
    0.08075646396731079,
    0.00021219165559888185,
    0.002121028514993012,
    0.001299172312425607,
    0.0004170454340054568,
    0.0032878564445547203,
    0.00046522514220469745,
    0.030414855538847443,
    0.0,
    0.27178387954971994,
    0.053770382125282803,
    8.224992810220655,
    0.0,
    0.27071590627695646,
    0.053801251581163535,
    8.057798157658075,
    0.11880290558456959,
    0.008223314236575277,
    0.0032276749379688096,
    0.0003335973451453809,
    0.003477383816981481,
    0.0036865156665674597,
    0.0022198222824084722,
    0.018796239281066583,
    0.004349418640697398,
    0.0024045193034457953
  ],
  "attributes": {
    "entropy": 5.8,
    "n_distinct": 160,
    "shuffle_ratio": 5.85,
    "content_type": "ordering-dependent",
    "description": "Sequential structure is critical \u2014 shuffling the bytes destroys the signature."
  }
}